beignet/__init__.py
beignet/_add_chebyshev_polynomial.py
beignet/_add_laguerre_polynomial.py
beignet/_add_legendre_polynomial.py
beignet/_add_physicists_hermite_polynomial.py
beignet/_add_polynomial.py
beignet/_add_probabilists_hermite_polynomial.py
beignet/_apply_euler_angle.py
beignet/_apply_quaternion.py
beignet/_apply_rotation_matrix.py
beignet/_apply_rotation_vector.py
beignet/_apply_transform.py
beignet/_bisect.py
beignet/_canonicalize_quaternion.py
beignet/_chandrupatla.py
beignet/_chebyshev_extrema.py
beignet/_chebyshev_gauss_quadrature.py
beignet/_chebyshev_interpolation.py
beignet/_chebyshev_polynomial_companion.py
beignet/_chebyshev_polynomial_domain.py
beignet/_chebyshev_polynomial_from_roots.py
beignet/_chebyshev_polynomial_one.py
beignet/_chebyshev_polynomial_power.py
beignet/_chebyshev_polynomial_roots.py
beignet/_chebyshev_polynomial_to_polynomial.py
beignet/_chebyshev_polynomial_vandermonde.py
beignet/_chebyshev_polynomial_vandermonde_2d.py
beignet/_chebyshev_polynomial_vandermonde_3d.py
beignet/_chebyshev_polynomial_weight.py
beignet/_chebyshev_polynomial_x.py
beignet/_chebyshev_polynomial_zero.py
beignet/_chebyshev_zeros.py
beignet/_compose_euler_angle.py
beignet/_compose_quaternion.py
beignet/_compose_rotation_matrix.py
beignet/_compose_rotation_vector.py
beignet/_convolve.py
beignet/_default_dtype_manager.py
beignet/_differentiate_chebyshev_polynomial.py
beignet/_differentiate_laguerre_polynomial.py
beignet/_differentiate_legendre_polynomial.py
beignet/_differentiate_physicists_hermite_polynomial.py
beignet/_differentiate_polynomial.py
beignet/_differentiate_probabilists_hermite_polynomial.py
beignet/_dihedral_angle.py
beignet/_divide_chebyshev_polynomial.py
beignet/_divide_laguerre_polynomial.py
beignet/_divide_legendre_polynomial.py
beignet/_divide_physicists_hermite_polynomial.py
beignet/_divide_polynomial.py
beignet/_divide_probabilists_hermite_polynomial.py
beignet/_euler_angle_identity.py
beignet/_euler_angle_magnitude.py
beignet-0.0.13.dist-info/licenses/LICENSE
beignet-0.0.13.dist-info/METADATA
beignet-0.0.13.dist-info/WHEEL
beignet-0.0.13.dist-info/top_level.txt
beignet-0.0.13.dist-info/RECORD
