Metadata-Version: 2.4
Name: beignet
Version: 0.0.13
Author-email: Allen Goodman <allen.goodman@icloud.com>, Joseph Kleinhenz <kleinhej@gene.com>
License: Copyright © 2024 Genentech, Inc.
Requires-Python: >=3.10
License-File: LICENSE
Requires-Dist: biotite
Requires-Dist: einops>=0.8.1
Requires-Dist: fastpdb
Requires-Dist: numpy>=2
Requires-Dist: optree
Requires-Dist: pooch
Requires-Dist: torch
Requires-Dist: tqdm
Provides-Extra: all
Requires-Dist: beignet[datasets,docs,mdtraj,test]; extra == "all"
Provides-Extra: datasets
Requires-Dist: biopython; extra == "datasets"
Requires-Dist: lmdb; extra == "datasets"
Requires-Dist: pandas; extra == "datasets"
Requires-Dist: pooch; extra == "datasets"
Provides-Extra: docs
Requires-Dist: mkdocs-material; extra == "docs"
Requires-Dist: mkdocstrings[python]; extra == "docs"
Provides-Extra: mdtraj
Requires-Dist: mdtraj; extra == "mdtraj"
Requires-Dist: netcdf4; extra == "mdtraj"
Provides-Extra: test
Requires-Dist: hypothesis; extra == "test"
Requires-Dist: pytest; extra == "test"
Requires-Dist: pytest-mock; extra == "test"
Requires-Dist: scipy; extra == "test"
Dynamic: license-file
